right_triangle.py
right_triangle-0.2.0.dist-info/LICENSE
right_triangle-0.2.0.dist-info/METADATA
right_triangle-0.2.0.dist-info/WHEEL
right_triangle-0.2.0.dist-info/top_level.txt
right_triangle-0.2.0.dist-info/RECORD
