Metadata-Version: 2.1
Name: right-triangle
Version: 0.2.0
Summary: Simple Python package that can be used to do calculations with right-angled triangles
Home-page: https://github.com/lautnerb/right-triangle
Author: Balazs Lautner
Author-email: lautner.balazs@gmail.com
License: MIT
Platform: UNKNOWN
Classifier: Programming Language :: Python :: 3
Classifier: License :: OSI Approved :: MIT License
Classifier: Operating System :: OS Independent
Classifier: Topic :: Scientific/Engineering :: Mathematics
Classifier: Typing :: Typed
Requires-Python: ~=3.8
